pyneo/__init__.py
pyneo/connection.py
pyneo/data.py
pyneo-0.2.0.dist-info/LICENSE
pyneo-0.2.0.dist-info/METADATA
pyneo-0.2.0.dist-info/WHEEL
pyneo-0.2.0.dist-info/top_level.txt
pyneo-0.2.0.dist-info/RECORD
